examples/__init__.py
examples/box.py
examples/flowers.py
madison_wcb/__init__.py
madison_wcb/madison_wcb.py
madison_wcb/wcb.py
madison_wcb/examples/__init__.py
madison_wcb/examples/box.py
madison_wcb/examples/circle.py
madison_wcb/examples/flowers.py
madison_wcb/examples/spiky_circle.py
madison_wcb-0.1.13.dist-info/DESCRIPTION.rst
madison_wcb-0.1.13.dist-info/METADATA
madison_wcb-0.1.13.dist-info/RECORD
madison_wcb-0.1.13.dist-info/WHEEL
madison_wcb-0.1.13.dist-info/metadata.json
madison_wcb-0.1.13.dist-info/top_level.txt
