Metadata-Version: 2.0
Name: madison-wcb
Version: 0.1.13
Summary: A library that allows users to directly control a WaterColorBot by writing Python code.
Home-page: http://github.com/jrheard/madison_wcb
Author: JR Heard
Author-email: jrrrheard@gmail.com
License: MIT
Platform: UNKNOWN
Requires-Dist: requests
